CytOpT/CytOpt.py
CytOpT/__init__.py
CytOpT/__main__.py
CytOpT/cytoptVersion.py
CytOpT/descentAscent.py
CytOpT/labelPropSto.py
CytOpT/main.py
CytOpT/minmaxSwapping.py
CytOpT/plots.py
tests/Bland_Altman_Target_Full_HIPC.py
tests/Comparison_Optimization_Ten_Classes.py
tests/CytOpt_HIPC_Data.py
tests/TwoClasses_TwoDimensions.py
tests/__init__.py
tests/data/__init__.py
CytOpT-0.0.9.dist-info/LICENCE.txt
CytOpT-0.0.9.dist-info/METADATA
CytOpT-0.0.9.dist-info/WHEEL
CytOpT-0.0.9.dist-info/entry_points.txt
CytOpT-0.0.9.dist-info/top_level.txt
CytOpT-0.0.9.dist-info/RECORD
