Metadata-Version: 2.1
Name: CytOpT
Version: 0.0.9
Summary: CytOpT
Home-page: 
Author: ['Paul Freulon', 'Kalidou BA', 'Boris Hejblum']
Author-email: boris.hejblum@u-bordeaux.fr
License: MIT
Project-URL: Article, https://arxiv.org/abs/2006.09003
Project-URL: CytOpT pypi, https://github.com/sistm/CytOpt-python
Keywords: cytOpT
Platform: Any
Classifier: Development Status :: 5 - Production/Stable
Classifier: Intended Audience :: Developers
Classifier: Intended Audience :: Science/Research
Classifier: Topic :: Scientific/Engineering :: Bio-Informatics
Classifier: Topic :: Software Development :: Libraries :: Python Modules
Classifier: Operating System :: OS Independent
Classifier: License :: OSI Approved :: MIT License
Classifier: Programming Language :: Python :: 3.6
Classifier: Programming Language :: Python :: 3.7
Classifier: Programming Language :: Python :: 3.8
License-File: LICENCE.txt
Requires-Dist: numpy (~=1.21.4)
Requires-Dist: scipy (~=1.7.2)
Requires-Dist: setuptools (==59.4.0)
Requires-Dist: pandas (~=1.3.4)
Requires-Dist: scikit-learn (~=1.0.1)
Requires-Dist: matplotlib (~=3.5.0)
Requires-Dist: seaborn (~=0.11.2)
Requires-Dist: pyqt5 (<5.13)
Requires-Dist: pyqtwebengine (<5.13)
Requires-Dist: jedi (==0.17.2)
Requires-Dist: parso (==0.7.0)
Requires-Dist: sphinx
Requires-Dist: sphinx-rtd-theme
